gpu_check/__init__.py
gpu_check/service/__init__.py
gpu_check/service/__main__.py
jupyterhub_enverge_gpu_check-0.0.2.dist-info/METADATA
jupyterhub_enverge_gpu_check-0.0.2.dist-info/WHEEL
jupyterhub_enverge_gpu_check-0.0.2.dist-info/top_level.txt
jupyterhub_enverge_gpu_check-0.0.2.dist-info/RECORD
