Metadata-Version: 2.4
Name: jupyterhub-enverge-gpu-check
Version: 0.0.2
Summary: JupyterHub GPU Resource Usage Analyzer
Home-page: https://github.com/Enverge-Labs/gpu_check
Author: Tudor M
Author-email: tudor@enverge.ai
License: 3 Clause BSD
Requires-Python: >=3.10
Requires-Dist: jupyterhub>=4.1.6
Requires-Dist: tornado>=6.0.0
Provides-Extra: dev
Requires-Dist: pytest>=7.0.0; extra == "dev"
Dynamic: author
Dynamic: author-email
Dynamic: description
Dynamic: description-content-type
Dynamic: home-page
Dynamic: license
Dynamic: provides-extra
Dynamic: requires-dist
Dynamic: requires-python
Dynamic: summary
